LICENSE
MANIFEST.in
requirements.txt
setup.py
dinette/__init__.py
dinette/__init__.pyc
dinette/admin.py
dinette/admin.pyc
dinette/extra_settings.py
dinette/extra_settings.pyc
dinette/forms.py
dinette/forms.pyc
dinette/middleware.py
dinette/models.py
dinette/models.pyc
dinette/search.py
dinette/search_indexes.py
dinette/urls.py
dinette/urls.pyc
dinette/views.py
dinette/views.pyc
dinette.egg-info/PKG-INFO
dinette.egg-info/SOURCES.txt
dinette.egg-info/dependency_links.txt
dinette.egg-info/top_level.txt
dinette/fixtures/dinette_testmaker.json
dinette/fixtures/test_data.json
dinette/libs/__init__.py
dinette/libs/__init__.pyc
dinette/libs/postmarkup.py
dinette/libs/postmarkup.pyc
dinette/management/__init__.py
dinette/management/__init__.pyc
dinette/management/commands/__init__.py
dinette/management/commands/daily_updates.py
dinette/media/CACHE/css/1e269173dd01.css
dinette/media/CACHE/css/bc206d866e36.css
dinette/media/CACHE/js/957d88491f1d.js
dinette/migrations/0001_initial.py
dinette/migrations/0002_reply_num.py
dinette/migrations/0003_num_replies.py
dinette/migrations/0004_populate_values.py
dinette/migrations/0005_unique_profiles.py
dinette/migrations/0006_profile.py
dinette/migrations/0007_profile_last_sessiom.py
dinette/migrations/0008_nav_links.py
dinette/migrations/0009_markup.py
dinette/migrations/0010_migrate_reply_markup.py
dinette/migrations/0011_userprofile_slug.py
dinette/migrations/0012_populate_slugs.py
dinette/migrations/0013_auto__add_unique_dinetteuserprofile_slug.py
dinette/migrations/0014_add_subscriptions.py
dinette/migrations/0015_add_digest_subscription.py
dinette/migrations/__init__.py
dinette/static/dinette/google.png
dinette/static/dinette/openid.png
dinette/static/dinette/twitter.png
dinette/static/dinette/yahoo.png
dinette/static/dinette/css/Oxygen_ie6.css
dinette/static/dinette/css/Oxygen_ie7.css
dinette/static/dinette/css/djorumstyle.css
dinette/static/dinette/css/oxygen.css
dinette/static/dinette/css/oxygen_cs.css
dinette/static/dinette/images/ajaximage.gif
dinette/static/dinette/openid/css/openid.css
dinette/static/dinette/openid/images/aol.gif
